FlipFlops.sv
/////////////////////////////
//Sang Woo Shin 15372
//FlipFlops(D y T)
//Procesador
////////////////////////////

module FFT(input logic clk,T,reset, output logic Q);
	
always @(posedge clk or posedge reset)begin
	if (T && clk)begin
		Q=~Q;
	end
	
	if (reset)begin
		Q=0;
	end
end

endmodule

module FFD8 #(parameter N=8)(input logic clk, reset, input logic [N-1:0] D, output logic [N-1:0] Q);

always @(posedge clk or posedge reset)begin
	if (clk)begin
		Q<=D;
	end
	
	if (reset)begin
		Q<=0;
	end
	
	
	end
endmodule

module FFD4 #(parameter N=4)(input logic clk, reset, input logic [N-1:0] D, output logic [N-1:0] Q);

always @(posedge clk or posedge reset)begin
	if (clk)begin
		Q<=D;
	end
	
	if (reset)begin
		Q<=0;
	end
	
	
	end
endmodule

module FFD2 #(parameter N=2)(input logic clk, reset, input logic [N-1:0] D, output logic [N-1:0] Q);

always @(posedge clk or posedge reset)begin
	
	if (clk)begin
		Q<=D;
	end
	
	if (reset)begin
		Q<=0;
	end
end

endmodule

TristateBuffer.sv
/////////////////////////////
//Sang Woo Shin 15372
//Tristates
//Procesador
////////////////////////////

module TristateB #(parameter N=4)(input logic tri_en, input logic [N-1:0] entrada, output logic [N-1:0] salida);

	assign salida = (tri_en) ? entrada: 4'bz;

endmodule

DecoderIO.sv
/////////////////////////////
//Sang Woo Shin 15372
//Decoders for I/O
//Procesador
////////////////////////////

module Decoder #(parameter N=4,M=16)(input logic load,clk,input logic [N-1:0] binary, output logic [M-1:0] onehot);
	
	
	always @(posedge clk)begin
		if (load)begin
			case(binary)
				4'd0:  onehot<=16'b0000000000000001;
				4'd1:  onehot<=16'b0000000000000010;
				4'd2:  onehot<=16'b0000000000000100;
				4'd3:  onehot<=16'b0000000000001000;
				4'd4:  onehot<=16'b0000000000010000;
				4'd5:  onehot<=16'b0000000000100000;
				4'd6:  onehot<=16'b0000000001000000;
				4'd7:  onehot<=16'b0000000010000000;
				4'd8:  onehot<=16'b0000000100000000;
				4'd9:  onehot<=16'b0000001000000000;
				4'd10: onehot<=16'b0000010000000000;
				4'd11: onehot<=16'b0000100000000000;
				4'd12: onehot<=16'b0001000000000000;
				4'd13: onehot<=16'b0010000000000000;
				4'd14: onehot<=16'b0100000000000000;
				4'd15: onehot<=16'b1000000000000000;
				default: onehot<=16'b0;
			endcase
		end
		if (~load) begin
			onehot<=16'b0;
			
		end
		end
	
	


endmodule

RAM.sv
/////////////////////////////
//Sang Woo Shin 15372
//RAM(síncrono Single Port)
//Procesador
////////////////////////////

module RAM #(parameter N=12, M=4)(input logic clk, we,cs, input logic [N-1:0] address, inout wire [M-1:0] data);

logic [M-1:0] memory [0:4000];
logic [M-1:0] data_out;

assign data = (cs &&  ! we) ? data_out : 4'bz;

always @(posedge ~clk)begin //WRITE
	if(cs && we)begin
		memory[address]<=data;
	

	end
		//READ
	if(cs && !we)begin
		data_out<=memory[address];
	
	end
end

endmodule

ALU.sv
//---------------------------------------
//Sang Woo Shin 15372
//Lab 7 - PC
//----------------------------------------

module ALU #(parameter N=4)(input logic [N-1:0] A,B, input logic [4:0] S, input logic nCin, output logic Cout, eq, output logic [N-1:0] Result);
  
  logic [N:0] Oper,Ans;
  
  always@(*)begin
    
    case(S)
      5'b00000: Ans<=A;
      5'b00110: Ans<=A-B;
      5'b11010: Ans<=B;
      5'b01001: Ans<=A+B;
      5'b10001: Ans<=A[3:0]~|B[3:0];
	default: Ans=0;
	
    endcase
      
    Cout=Ans[4];
    Result<={Ans[3:0]};
    
    if (Ans[3:0]==0)begin
      eq=1;
    end
    else begin
      eq=0;
    end
  end
  endmodule

ROM.sv
/////////////////////////////
//Sang Woo Shin 15372
//ROMs
//Procesador
////////////////////////////

module ProgROM #(parameter N=12,M=8)(input logic [N-1:0] address, output logic[M-1:0] ProgOut);

	logic [N-1:0] memory [0:500];
	
	assign ProgOut=memory[address];
	
	initial begin
		$readmemb("CodeROM.list",memory);
	end
endmodule

module ControlROM #(parameter N=7,M=16)(input logic [N-1:0] address, output logic[M-1:0] ProgOut);

	always @(*)begin
		casex(address) //i3-i2-i1-i0-/C-/Z-Phase  
			7'bxxxxxx0: ProgOut<=16'b1111100000110111; //any
			7'b00000x1: ProgOut<=16'b0011100000110111; //JC
			7'b00001x1: ProgOut<=16'b1111100000110111; //JC
			7'b00010x1: ProgOut<=16'b1111100000110111; //JNC
			7'b00011x1: ProgOut<=16'b0011100000110111; //JNC
			7'b0010xx1: ProgOut<=16'b0110000110111101; //CMPI
			7'b0011xx1: ProgOut<=16'b1110000110011111; //CMPM
			7'b0100xx1: ProgOut<=16'b0100011010111101; //LIT
			7'b0101xx1: ProgOut<=16'b0100011010111011; //IN
			7'b0110xx1: ProgOut<=16'b1100011010011111; //LD
			7'b0111xx1: ProgOut<=16'b1111100000000111; //ST
			7'b1000x01: ProgOut<=16'b0011100000110111; //JZ
			7'b1000x11: ProgOut<=16'b1111100000110111; //JZ
			7'b1001x01: ProgOut<=16'b1111100000110111; //JNZ
			7'b1001x11: ProgOut<=16'b0011100000110111; //JNZ
			7'b1010xx1: ProgOut<=16'b0100101001111101; //ADDI
			7'b1011xx1: ProgOut<=16'b1100101001011111; //ADDM
			7'b1100xx1: ProgOut<=16'b0011100000110111; //JMP
			7'b1101xx1: ProgOut<=16'b0111100000110110; //OUT
			7'b1110xx1: ProgOut<=16'b0100010001111101; //NORI
			7'b1111xx1: ProgOut<=16'b1100010001011111; //NORM
			default: 	ProgOut<=16'b0111100000111111;
		endcase
	
	end
endmodule

ProgramCounter.sv
//---------------------------------------
//Sang Woo Shin 15372
//Lab 7 - PC
//----------------------------------------



module PC #(parameter N=12)(input logic [N-1:0] LOAD, input logic reset,loadE,incPC, clk, output logic [N-1:0] INS);
  
  always @ (posedge clk or posedge reset)begin
    if (reset)begin
    INS<=0;
    end
    else begin
      
      if (loadE)INS<=LOAD;
      
      if (incPC) INS<=INS+1;
      
    end
    
  end
    
endmodule

Board.sv
/////////////////////////////
//Sang Woo Shin 15372
//Breadboard-PCB
//Procesador
////////////////////////////

`include "ProgramCounter.sv"
`include "ALU.sv"
`include "FlipFlops.sv"
`include "ROM.sv"
`include "TristateBuffer.sv"
`include "RAM.sv"
`include "DecoderIO.sv"

module Board #(parameter N=4)(input logic clk, reset, input logic [N-1:0] In0,In1,In2, output logic C,Z, output logic [N-1:0] Out0,Out1,Out2,Accu);

wire [15:0] control;
wire [3:0] operand,ALUR,Aout;
wire [11:0] address,loadAdd;
wire [7:0] progbyte;
wire [6:0] uRomAddress;
wire [1:0] CarryZero;
wire [3:0] databus;
wire [15:0] outputE;
wire [15:0] inputE;


PC ProgCounter(.LOAD(loadAdd),.reset(reset),.loadE(~control[14]),.incPC(control[15]),.clk(clk),.INS(address));

FFT Phase(.clk(clk),.reset(reset),.T(1'b1),.Q(uRomAddress[0]));

FFD2 CZ(.clk((control[12] && ~uRomAddress[0])),.reset(reset),.D(~CarryZero),.Q(uRomAddress[2:1]));

ControlROM uROM(.address(uRomAddress),.ProgOut(control));

ProgROM pROM(.address(address),.ProgOut(progbyte));

FFD8 Fetch(.clk(uRomAddress[0]),.reset(reset),.D(progbyte),.Q({uRomAddress[6:3],operand}));

TristateB Oper(.tri_en(~control[1] ),.entrada(operand),.salida(databus));

FFD4 A(.clk(~control[13] && ~uRomAddress[0]),.reset(reset),.D(ALUR),.Q(Aout));

ALU ALU(.A(Aout),.B(databus),.S(control[10:6]),.nCin(control[11]),.Cout(CarryZero[1]),.eq(CarryZero[0]),.Result(ALUR));

TristateB TriALU(.tri_en(~control[3]),.entrada(ALUR),.salida(databus));

RAM DRAM(.clk(clk), .we(~control[4]), .cs(~control[5]), .address(loadAdd),.data(databus));

Decoder OutDecode(.load(~control[0]),.clk(control[13]),.binary(operand),.onehot(outputE)); //maybe clk(clk)

Decoder InputDecode(.load(~control[2]),.clk(control[13]),.binary(operand),.onehot(inputE));

TristateB Input0(.tri_en(inputE[0]),.entrada(In0),.salida(databus));

TristateB Input1(.tri_en(inputE[1]),.entrada(In1),.salida(databus));

TristateB Input2(.tri_en(inputE[2]),.entrada(In2),.salida(databus));

FFD4 Output0(.clk(outputE[0]  && ~uRomAddress[0]),.reset(reset),.D(databus),.Q(Out0));

FFD4 Output1(.clk(outputE[1] && ~uRomAddress[0]),.reset(reset),.D(databus),.Q(Out1));

FFD4 Output2(.clk(outputE[2]  && ~uRomAddress[0]),.reset(reset),.D(databus),.Q(Out2));

assign loadAdd= {operand,progbyte};

assign Accu = Aout;

assign C = ~uRomAddress[2];

assign Z = ~uRomAddress[1];



endmodule

tbProcessor.sv
`include "Board.sv"


module testbench();
  logic clk = 1, reset;
  logic [3:0] PUSHBUTTONS0, PUSHBUTTONS1, PUSHBUTTONS2;
  logic PHASE, C_FLAG, Z_FLAG;
  logic [3:0] INSTR, OPERAND, DATA_BUS, ACCU, PORT0, PORT1, PORT2;
  logic [7:0] PROGRAM_BYTE;
  logic [11:0] PC, ADDRESS_RAM;
  real points = 0;

  Board Proto(.clk(clk), .reset(reset), .In0(PUSHBUTTONS0), .In1(PUSHBUTTONS1), .In2(PUSHBUTTONS2), 
  .C(C_FLAG), .Z(Z_FLAG), .Out0(PORT0), .Out1(PORT1), .Out2(PORT2), .Accu(ACCU));

  initial begin
    reset = 0;
    #1 reset = 1;
    #1 reset = 0;
    PUSHBUTTONS0 = 4'b0110;
    PUSHBUTTONS1 = 4'b0100;
    PUSHBUTTONS2 = 4'b0001;
    //$display("\t\ttime:\tphase:\tPC:\tProgramByte:\tInstr:\tOprnd:\tRAM Addr:\tData Bus:\tAccu:\tC:\tZ:\tOut:\tIn:\t");
    //$monitor("%d\t%b\t%h\t%b\t%b\t%b\t%b\t%b\t\t%b\t%b\t%b\t%b\t%b", $time, PHASE, PC, PROGRAM_BYTE, INSTR, OPERAND, ADDRESS_RAM, DATA_BUS, ACCU, C_FLAG, Z_FLAG, FF_OUT, PUSHBUTTONS);
  end
  initial
    begin
  	  $dumpfile("dump.vcd");
  	  $dumpvars(1);
    end

  initial
    #1000 $finish;

  always
    #5 clk = ~clk;
	
	
   always @ (clk) begin
    case ($time)
      30: begin
        if (ACCU === 4'b1001) begin
          points = points + 5; $display("LIT funciona bien. Nota : %d", points); end
        else
          $display("LIT NO funciona bien. Nota: %d", points);
      end
      50: begin
        if (ACCU === 4'b1010) begin
          points = points + 5; $display("ADDI funciona bien. Nota : %d", points); end
        else
          $display("ADDI NO funciona bien. Nota: %d", points);
      end
      70: begin
        if (ACCU === 4'b0101) begin
          points = points + 5; $display("NORI funciona bien. Nota : %d", points); end
        else
          $display("NORI NO funciona bien. Nota: %d", points);
      end
      110: begin
        if (Z_FLAG === 1) begin
          points = points + 10; $display("CMPI & Z_FLAG funcionan bien. Nota: %d", points);
          $display("Felicitaciones! Todas las instrucciones con literales funcionan :)");
        end
        else
          $display("CMPI & Z_FLAG NO funcionan bien. Nota: %d", points);
      end
      150: begin
        if (ACCU === 4'b0000 && C_FLAG === 1) begin
          points = points + 5; $display("C_FLAG funciona bien. Nota : %d", points);
          $display("Felicitaciones! Todas las banderas funcionan bien! :D");
        end
        else
          $display("C_FLAG NO funciona bien. Nota: %d", points);
      end
      230: begin
      if (ACCU === 4'b1111) begin
        points = points + 15; $display("RAM (ST & LD) funciona bien. Nota : %d", points);
      end
      else
        $display("RAM (ST & LD) NO funciona bien. Nota: %d", points);
    end
      270: begin
        if (PORT0 === 4'b1000)
          $display("PORT0 funciona bien.");
        else
          $display("PORT0 NO funciona bien.");
      end
      310: begin
        if (PORT1 === 4'b0110)
          $display("PORT1 funciona bien.");
        else
          $display("PORT1 NO funciona bien.");
      end
      350: begin
        if (PORT2 === 4'b0001) begin
          points = points + 10; $display("PORT2 funciona bien. Nota: %d", points); end
        else
          $display("PORT2 NO funciona bien.");
      end
      370: begin
        if (ACCU === 4'b0110)
          $display("IN0 funciona bien.");
        else
          $display("IN0 NO funciona bien.");
      end
      390: begin
        if (ACCU === 4'b0100)
          $display("IN1 funciona bien.");
        else
          $display("IN1 NO funciona bien.");
      end
      410: begin
        if (ACCU === 4'b0001) begin
          points = points + 10; $display("IN2 funciona bien. Nota: %d", points); end
        else
          $display("IN2 NO funciona bien.");
      end
      470: begin
        if (ACCU === 4'b0000 && Z_FLAG === 1 && C_FLAG === 1) begin
          points = points + 5; $display("ADDM funciona bien. Nota: %d", points); end
        else
          $display("ADDM NO funciona bien.");
      end
      510: begin
        if (ACCU === 4'b0110) begin
          points = points + 5; $display("NORM funciona bien. Nota: %d", points); end
        else
          $display("NORM NO funciona bien.");
      end
      530: begin
        if (Z_FLAG === 0) begin
          $display("CMPM parece funcionar bien. Nota: %d", points); end
        else
          $display("CMPM NO funciona bien.");
      end
      570: begin
        if (Z_FLAG === 1) begin
          points = points + 5; $display("CMPM funciona bien. Nota: %d", points); end
        else
          $display("CMPM NO funciona bien.");
      end
      610: begin
        if (ACCU === 4'b1010) begin
          points = points + 4; $display("JMP funciona bien. Nota: %d", points); end
        else
          $display("JMP NO funciona bien.");
      end
      650: begin
        if (ACCU === 4'b1011) begin
          points = points + 4; $display("JNC funciona bien. Nota: %d", points); end
        else
          $display("JNC NO funciona bien.");
      end
      690: begin
        if (ACCU === 4'b1100) begin
          points = points + 4; $display("JNZ funciona bien. Nota: %d", points); end
        else
          $display("JNZ NO funciona bien.");
      end
      750: begin
        if (ACCU === 4'b0001) begin
          points = points + 4; $display("JZ funciona bien. Nota: %d", points); end
        else
          $display("JZ NO funciona bien.");
      end
      810: begin
        if (ACCU === 4'b0010) begin
          points = points + 4; $display("JC funciona bien. Nota: %d", points); end
        else
          $display("JC NO funciona bien.");
      end
    endcase
  end
endmodule

dump.vcd
$date
	Fri Nov 16 18:53:13 2018
$end
$version
	Icarus Verilog
$end
$timescale
	1s
$end
$scope module testbench $end
$var wire 1 ! Z_FLAG $end
$var wire 4 " PORT2 [3:0] $end
$var wire 4 # PORT1 [3:0] $end
$var wire 4 $ PORT0 [3:0] $end
$var wire 1 % C_FLAG $end
$var wire 4 & ACCU [3:0] $end
$var reg 4 ' PUSHBUTTONS0 [3:0] $end
$var reg 4 ( PUSHBUTTONS1 [3:0] $end
$var reg 4 ) PUSHBUTTONS2 [3:0] $end
$var reg 1 * clk $end
$var reg 1 + reset $end
$var real 1 , points $end
$upscope $end
$enddefinitions $end
#0
$dumpvars
r0 ,
0+
1*
bx )
bx (
bx '
bx &
x%
bx $
bx #
bx "
x!
$end
#1
1%
1!
b0 &
b0 $
b0 #
b0 "
1+
#2
b1 )
b100 (
b110 '
0+
#5
0*
#10
1*
#15
0*
#20
0%
0!
b1001 &
1*
#25
0*
#30
r5 ,
1*
#35
0*
#40
b1010 &
1*
#45
0*
#50
r10 ,
1*
#55
0*
#60
b101 &
1*
#65
0*
#70
r15 ,
1*
#75
0*
#80
1%
1*
#85
0*
#90
1*
#95
0*
#100
0%
1!
1*
#105
0*
#110
r25 ,
1*
#115
0*
#120
0!
b1111 &
1*
#125
0*
#130
1*
#135
0*
#140
1%
1!
b0 &
1*
#145
0*
#150
r30 ,
1*
#155
0*
#160
0%
0!
b1111 &
1*
#165
0*
#170
1*
#175
0*
#180
1*
#185
0*
#190
1*
#195
0*
#200
b1 &
1*
#205
0*
#210
1*
#215
0*
#220
b1111 &
1*
#225
0*
#230
r45 ,
1*
#235
0*
#240
b1000 &
1*
#245
0*
#250
1*
#255
0*
#260
b1000 $
1*
#265
0*
#270
1*
#275
0*
#280
b110 &
1*
#285
0*
#290
1*
#295
0*
#300
b110 #
1*
#305
0*
#310
1*
#315
0*
#320
b1 &
1*
#325
0*
#330
1*
#335
0*
#340
b1 "
1*
#345
0*
#350
r55 ,
1*
#355
0*
#360
b110 &
1*
#365
0*
#370
1*
#375
0*
#380
b100 &
1*
#385
0*
#390
1*
#395
0*
#400
b1 &
1*
#405
0*
#410
r65 ,
1*
#415
0*
#420
1*
#425
0*
#430
1*
#435
0*
#440
b1111 &
1*
#445
0*
#450
1*
#455
0*
#460
1%
1!
b0 &
1*
#465
0*
#470
r70 ,
1*
#475
0*
#480
0%
0!
b1000 &
1*
#485
0*
#490
1*
#495
0*
#500
b110 &
1*
#505
0*
#510
r75 ,
1*
#515
0*
#520
1*
#525
0*
#530
1*
#535
0*
#540
b1 &
1*
#545
0*
#550
1*
#555
0*
#560
1!
1*
#565
0*
#570
r80 ,
1*
#575
0*
#580
0!
1*
#585
0*
#590
1*
#595
0*
#600
b1010 &
1*
#605
0*
#610
r84 ,
1*
#615
0*
#620
1*
#625
0*
#630
1*
#635
0*
#640
b1011 &
1*
#645
0*
#650
r88 ,
1*
#655
0*
#660
1*
#665
0*
#670
1*
#675
0*
#680
b1100 &
1*
#685
0*
#690
r92 ,
1*
#695
0*
#700
1!
b0 &
1*
#705
0*
#710
1*
#715
0*
#720
1*
#725
0*
#730
1*
#735
0*
#740
0!
b1 &
1*
#745
0*
#750
r96 ,
1*
#755
0*
#760
1%
1!
b0 &
1*
#765
0*
#770
1*
#775
0*
#780
0%
1*
#785
0*
#790
1*
#795
0*
#800
0!
b10 &
1*
#805
0*
#810
r100 ,
1*
