FlipFlops.sv
/////////////////////////////
//Sang Woo Shin 15372
//FlipFlops(D y T)
//Procesador
////////////////////////////

module FFT(input logic clk,T,reset, output logic Q);
	
always @(posedge clk or posedge reset)begin
	if (T && clk)begin
		Q=~Q;
	end
	
	if (reset)begin
		Q=0;
	end
end

endmodule

module FFD8 #(parameter N=8)(input logic clk, reset, input logic [N-1:0] D, output logic [N-1:0] Q);

always @(posedge clk or posedge reset)begin
	if (clk)begin
		Q<=D;
	end
	
	if (reset)begin
		Q<=0;
	end
	
	
	end
endmodule

module FFD4 #(parameter N=4)(input logic clk, reset, input logic [N-1:0] D, output logic [N-1:0] Q);

always @(posedge clk or posedge reset)begin
	if (clk)begin
		Q<=D;
	end
	
	if (reset)begin
		Q<=0;
	end
	
	
	end
endmodule

module FFD2 #(parameter N=2)(input logic clk, reset, input logic [N-1:0] D, output logic [N-1:0] Q);

always @(posedge clk or posedge reset)begin
	
	if (clk)begin
		Q<=D;
	end
	
	if (reset)begin
		Q<=0;
	end
end

endmodule

TristateBuffer.sv
/////////////////////////////
//Sang Woo Shin 15372
//Tristates
//Procesador
////////////////////////////

module TristateB #(parameter N=4)(input logic tri_en, input logic [N-1:0] entrada, output logic [N-1:0] salida);

	assign salida = (tri_en) ? entrada: 4'bz;

endmodule

DecoderIO.sv
/////////////////////////////
//Sang Woo Shin 15372
//Decoders for I/O
//Procesador
////////////////////////////

module Decoder #(parameter N=4,M=16)(input logic load,clk,input logic [N-1:0] binary, output logic [M-1:0] onehot);
	
	
	always @(posedge clk)begin
		if (load)begin
			case(binary)
				4'd0:  onehot<=16'b0000000000000001;
				4'd1:  onehot<=16'b0000000000000010;
				4'd2:  onehot<=16'b0000000000000100;
				4'd3:  onehot<=16'b0000000000001000;
				4'd4:  onehot<=16'b0000000000010000;
				4'd5:  onehot<=16'b0000000000100000;
				4'd6:  onehot<=16'b0000000001000000;
				4'd7:  onehot<=16'b0000000010000000;
				4'd8:  onehot<=16'b0000000100000000;
				4'd9:  onehot<=16'b0000001000000000;
				4'd10: onehot<=16'b0000010000000000;
				4'd11: onehot<=16'b0000100000000000;
				4'd12: onehot<=16'b0001000000000000;
				4'd13: onehot<=16'b0010000000000000;
				4'd14: onehot<=16'b0100000000000000;
				4'd15: onehot<=16'b1000000000000000;
				default: onehot<=16'b0;
			endcase
		end
		if (~load) begin
			onehot<=16'b0;
			
		end
		end
	
	


endmodule

RAM.sv
/////////////////////////////
//Sang Woo Shin 15372
//RAM(síncrono Single Port)
//Procesador
////////////////////////////

module RAM #(parameter N=12, M=4)(input logic clk, we,cs, input logic [N-1:0] address, inout wire [M-1:0] data);

logic [M-1:0] memory [0:4000];
logic [M-1:0] data_out;

assign data = (cs &&  ! we) ? data_out : 4'bz;

always @(posedge ~clk)begin //WRITE
	if(cs && we)begin
		memory[address]<=data;
	

	end
		//READ
	if(cs && !we)begin
		data_out<=memory[address];
	
	end
end

endmodule

ALU.sv
//---------------------------------------
//Sang Woo Shin 15372
//Lab 7 - PC
//----------------------------------------

module ALU #(parameter N=4)(input logic [N-1:0] A,B, input logic [4:0] S, input logic nCin, output logic Cout, eq, output logic [N-1:0] Result);
  
  logic [N:0] Oper,Ans;
  
  always@(*)begin
    
    case(S)
      5'b00000: Ans<=A;
      5'b00110: Ans<=A-B;
      5'b11010: Ans<=B;
      5'b01001: Ans<=A+B;
      5'b10001: Ans<=A[3:0]~|B[3:0];
	default: Ans=0;
	
    endcase
      
    Cout=Ans[4];
    Result<={Ans[3:0]};
    
    if (Ans[3:0]==0)begin
      eq=1;
    end
    else begin
      eq=0;
    end
  end
  endmodule

ROM.sv
/////////////////////////////
//Sang Woo Shin 15372
//ROMs
//Procesador
////////////////////////////

module ProgROM #(parameter N=12,M=8)(input logic [N-1:0] address, output logic[M-1:0] ProgOut);

	logic [N-1:0] memory [0:100];
	
	assign ProgOut=memory[address];
	
	initial begin
		$readmemb("CodeROM.list",memory);
	end
endmodule

module ControlROM #(parameter N=7,M=16)(input logic [N-1:0] address, output logic[M-1:0] ProgOut);

	always @(*)begin
		casex(address) //i3-i2-i1-i0-/C-/Z-Phase  
			7'bxxxxxx0: ProgOut<=16'b1111100000110111; //any
			7'b00000x1: ProgOut<=16'b0011100000110111; //JC
			7'b00001x1: ProgOut<=16'b1111100000110111; //JC
			7'b00010x1: ProgOut<=16'b1111100000110111; //JNC
			7'b00011x1: ProgOut<=16'b0011100000110111; //JNC
			7'b0010xx1: ProgOut<=16'b0110000110111101; //CMPI
			7'b0011xx1: ProgOut<=16'b1110000110011111; //CMPM
			7'b0100xx1: ProgOut<=16'b0100011010111101; //LIT
			7'b0101xx1: ProgOut<=16'b0100011010111011; //IN
			7'b0110xx1: ProgOut<=16'b1100011010011111; //LD
			7'b0111xx1: ProgOut<=16'b1111100000000111; //ST
			7'b1000x01: ProgOut<=16'b0011100000110111; //JZ
			7'b1000x11: ProgOut<=16'b1111100000110111; //JZ
			7'b1001x01: ProgOut<=16'b1111100000110111; //JNZ
			7'b1001x11: ProgOut<=16'b0011100000110111; //JNZ
			7'b1010xx1: ProgOut<=16'b0100101001111101; //ADDI
			7'b1011xx1: ProgOut<=16'b1100101001011111; //ADDM
			7'b1100xx1: ProgOut<=16'b0011100000110111; //JMP
			7'b1101xx1: ProgOut<=16'b0111100000110110; //OUT
			7'b1110xx1: ProgOut<=16'b0100010001111101; //NORI
			7'b1111xx1: ProgOut<=16'b1100010001011111; //NORM
			default: 	ProgOut<=16'b0111100000111111;
		endcase
	
	end
endmodule

ProgramCounter.sv
//---------------------------------------
//Sang Woo Shin 15372
//Lab 7 - PC
//----------------------------------------



module PC #(parameter N=12)(input logic [N-1:0] LOAD, input logic reset,loadE,incPC, clk, output logic [N-1:0] INS);
  
  always @ (posedge clk or posedge reset)begin
    if (reset)begin
    INS<=0;
    end
    else begin
      
      if (loadE)INS<=LOAD;
      
      if (incPC) INS<=INS+1;
      
    end
    
  end
    
endmodule

Board.sv
/////////////////////////////
//Sang Woo Shin 15372
//Breadboard-PCB
//Procesador
////////////////////////////

`include "ProgramCounter.sv"
`include "ALU.sv"
`include "FlipFlops.sv"
`include "ROM.sv"
`include "TristateBuffer.sv"
`include "RAM.sv"
`include "DecoderIO.sv"

module Board #(parameter N=4)(input logic clk, reset, input logic [N-1:0] In0,In1,In2, output logic C,Z, output logic [N-1:0] Out0,Out1,Out2,Accu);

wire [15:0] control;
wire [3:0] operand,ALUR,Aout;
wire [11:0] address,loadAdd;
wire [7:0] progbyte;
wire [6:0] uRomAddress;
wire [1:0] CarryZero;
wire [3:0] databus;
wire [15:0] outputE;
wire [15:0] inputE;


PC ProgCounter(.LOAD(loadAdd),.reset(reset),.loadE(~control[14]),.incPC(control[15]),.clk(clk),.INS(address));

FFT Phase(.clk(clk),.reset(reset),.T(1'b1),.Q(uRomAddress[0]));

FFD2 CZ(.clk(control[12]),.reset(reset),.D(CarryZero),.Q(uRomAddress[2:1]));

ControlROM uROM(.address(uRomAddress),.ProgOut(control));

ProgROM pROM(.address(address),.ProgOut(progbyte));

FFD8 Fetch(.clk(uRomAddress[0]),.reset(reset),.D(progbyte),.Q({uRomAddress[6:3],operand}));

TristateB Oper(.tri_en(~control[1]),.entrada(operand),.salida(databus));

FFD4 A(.clk(control[13]),.reset(reset),.D(ALUR),.Q(Aout));

ALU ALU(.A(Aout),.B(databus),.S(control[10:6]),.nCin(control[11]),.Cout(CarryZero[1]),.eq(CarryZero[0]),.Result(ALUR));

TristateB TriALU(.tri_en(~control[3]),.entrada(ALUR),.salida(databus));

RAM DRAM(.clk(clk), .we(~control[4]), .cs(~control[5]), .address(loadAdd),.data(databus));

Decoder OutDecode(.load(~control[0]),.clk(clk),.binary(operand),.onehot(outputE));

Decoder InputDecode(.load(~control[2]),.clk(clk),.binary(operand),.onehot(inputE));

TristateB Input0(.tri_en(inputE[0]),.entrada(In0),.salida(databus));

TristateB Input1(.tri_en(inputE[1]),.entrada(In1),.salida(databus));

TristateB Input2(.tri_en(inputE[2]),.entrada(In2),.salida(databus));

FFD4 Output0(.clk(outputE[0]),.reset(reset),.D(databus),.Q(Out0));

FFD4 Output1(.clk(outputE[1]),.reset(reset),.D(databus),.Q(Out1));

FFD4 Output2(.clk(outputE[2]),.reset(reset),.D(databus),.Q(Out2));

assign loadAdd= {operand,progbyte};

assign Accu = operand;

assign C = ~uRomAddress[2];

assign Z = ~uRomAddress[1];



endmodule

tbProcessor.sv
//---------------------------------------
//Sang Woo Shin 15372
//Lab 7 - Testbench
//Processor
//----------------------------------------

`include "Board.sv"



module testbench();
  
  parameter N=4;
  logic clk,reset,C,Z;
  logic [N-1:0] Accu,In0,In1,In2,Out0,Out1,Out2;
  logic [15:0] test;
  
  Board Processor(.clk(clk), .reset(reset), .C(C),.Z(Z), .Accu(Accu),.In0(In0),.In1(In1),.In2(In2),.Out0(Out0),.Out1(Out1),.Out2(Out2));
  
  initial begin
    $display("\t\tTime\t\t clk \t reset \t C \t Z \t Accu \t In0 \t In1 \t In2 \t Out0 \t Out1 \t Out2");
    $monitor("%d \t \t %b \t %b \t %b \t %b \t %d \t %d \t %d \t %d \t %d \t\t %d \t %d ",$time, clk,reset,C,Z,Accu, In0,In1,In2,Out0,Out1,Out2);
	
	
    //Initial values
    clk=0;
	reset=0;
	In0=0;
	In1=0;
	In2=0;
	
	
    //Start
	#1 reset=1;
	#1 reset=0;
	
	
  end
  
  initial begin
    #200 $finish;
  end
  
 always
    #2 clk = ~clk;
	
  
  initial 
    begin
  	  $dumpfile("dump.vcd");
  	  $dumpvars(1);
    end
endmodule

dump.vcd
$date
	Wed Nov 14 16:26:25 2018
$end
$version
	Icarus Verilog
$end
$timescale
	1s
$end
$scope module testbench $end
$var wire 1 ! Z $end
$var wire 4 " Out2 [3:0] $end
$var wire 4 # Out1 [3:0] $end
$var wire 4 $ Out0 [3:0] $end
$var wire 1 % C $end
$var wire 4 & Accu [3:0] $end
$var reg 4 ' In0 [3:0] $end
$var reg 4 ( In1 [3:0] $end
$var reg 4 ) In2 [3:0] $end
$var reg 1 * clk $end
$var reg 1 + reset $end
$upscope $end
$enddefinitions $end
#0
$dumpvars
0+
0*
b0 )
b0 (
b0 '
bx &
x%
bx $
bx #
bx "
x!
$end
#1
1%
1!
b0 &
b0 $
b0 #
b0 "
1+
#2
b111 &
0+
1*
#4
0*
#6
1*
#8
0*
#10
b10 &
1*
#12
0*
#14
1*
#16
0*
#18
b1 &
1*
#20
0*
#22
1*
#24
0*
#26
b1001 &
1*
#28
0*
#30
1*
#32
0*
#34
0!
b0 &
1*
#36
0*
#38
1*
#40
0*
#42
b1 &
1*
#44
0*
#46
0%
1!
1*
#48
0*
#50
1%
b0 &
1*
#52
0*
#54
1*
#56
0*
#58
b10 &
1*
#60
0*
#62
1*
#64
0*
#66
b1 &
1*
#68
0*
#70
1*
#72
0*
#74
b1001 &
1*
#76
0*
#78
1*
#80
0*
#82
0!
b0 &
1*
#84
0*
#86
1*
#88
0*
#90
b1 &
1*
#92
0*
#94
1!
1*
#96
0*
#98
0%
b0 &
1*
#100
0*
#102
1*
#104
0*
#106
b10 &
1*
#108
0*
#110
b1101 "
1*
#112
0*
#114
b0 &
1*
#116
0*
#118
1*
#120
0*
#122
b111 &
1*
#124
0*
#126
1%
1*
#128
0*
#130
b10 &
1*
#132
0*
#134
1*
#136
0*
#138
b1 &
1*
#140
0*
#142
1*
#144
0*
#146
b1001 &
1*
#148
0*
#150
1*
#152
0*
#154
0!
b0 &
1*
#156
0*
#158
1*
#160
0*
#162
b1 &
1*
#164
0*
#166
0%
1!
1*
#168
0*
#170
1%
b0 &
1*
#172
0*
#174
1*
#176
0*
#178
b10 &
1*
#180
0*
#182
1*
#184
0*
#186
b1 &
1*
#188
0*
#190
1*
#192
0*
#194
b1001 &
1*
