FlipFlops.sv
/////////////////////////////
//Sang Woo Shin 15372
//FlipFlops(D y T)
//Procesador
////////////////////////////

module FFT(input logic clk,T,reset, output logic Q);
	
always @(posedge clk or posedge reset)begin
	if (T && clk)begin
		Q=~Q;
	end
	
	if (reset)begin
		Q=0;
	end
end

endmodule

module FFD8 #(parameter N=8)(input logic clk, reset, input logic [N-1:0] D, output logic [N-1:0] Q);

always @(posedge clk or posedge reset)begin
	if (clk)begin
		Q<=D;
	end
	
	if (reset)begin
		Q<=0;
	end
	
	
	end
endmodule

module FFD4 #(parameter N=4)(input logic clk, reset, input logic [N-1:0] D, output logic [N-1:0] Q);

always @(posedge clk or posedge reset)begin
	if (clk)begin
		Q<=D;
	end
	
	if (reset)begin
		Q<=0;
	end
	
	
	end
endmodule

module FFD2 #(parameter N=2)(input logic clk, reset, input logic [N-1:0] D, output logic [N-1:0] Q);

always @(posedge clk or posedge reset)begin
	
	if (clk)begin
		Q<=D;
	end
	
	if (reset)begin
		Q<=0;
	end
end

endmodule

TristateBuffer.sv
/////////////////////////////
//Sang Woo Shin 15372
//Tristates
//Procesador
////////////////////////////

module TristateB #(parameter N=4)(input logic tri_en, input logic [N-1:0] entrada, output logic [N-1:0] salida);

	assign salida = (tri_en) ? entrada: 4'bz;

endmodule

DecoderIO.sv
/////////////////////////////
//Sang Woo Shin 15372
//Decoders for I/O
//Procesador
////////////////////////////

module Decoder #(parameter N=4,M=16)(input logic load,clk,input logic [N-1:0] binary, output logic [M-1:0] onehot);
	
	
	always @(posedge clk)begin
		if (load)begin
			case(binary)
				4'd0:  onehot<=16'b0000000000000001;
				4'd1:  onehot<=16'b0000000000000010;
				4'd2:  onehot<=16'b0000000000000100;
				4'd3:  onehot<=16'b0000000000001000;
				4'd4:  onehot<=16'b0000000000010000;
				4'd5:  onehot<=16'b0000000000100000;
				4'd6:  onehot<=16'b0000000001000000;
				4'd7:  onehot<=16'b0000000010000000;
				4'd8:  onehot<=16'b0000000100000000;
				4'd9:  onehot<=16'b0000001000000000;
				4'd10: onehot<=16'b0000010000000000;
				4'd11: onehot<=16'b0000100000000000;
				4'd12: onehot<=16'b0001000000000000;
				4'd13: onehot<=16'b0010000000000000;
				4'd14: onehot<=16'b0100000000000000;
				4'd15: onehot<=16'b1000000000000000;
				default: onehot<=16'b0;
			endcase
		end
		if (~load) begin
			onehot<=16'b0;
			
		end
		end
	
	


endmodule

RAM.sv
/////////////////////////////
//Sang Woo Shin 15372
//RAM(síncrono Single Port)
//Procesador
////////////////////////////

module RAM #(parameter N=12, M=4)(input logic clk, we,cs, input logic [N-1:0] address, inout wire [M-1:0] data);

logic [M-1:0] memory [0:4095];
logic [M-1:0] data_out;

assign data = (cs &&  ! we) ? data_out : 4'bz;

always @(posedge ~clk)begin //WRITE
	if(cs && we)begin
		memory[address]<=data;
	

	end
		//READ
	if(cs && !we)begin
		data_out<=memory[address];
	
	end
end

endmodule

ALU.sv
//---------------------------------------
//Sang Woo Shin 15372
//Lab 7 - PC
//----------------------------------------

module ALU #(parameter N=4)(input logic [N-1:0] A,B, input logic [4:0] S, input logic nCin, output logic Cout, eq, output logic [N-1:0] Result);
  
  logic [N:0] Oper,Ans;
  
  always@(*)begin
    
    case(S)
      5'b00000: Ans<={1'b0,A};
      5'b00110: Ans<=A-B;
      5'b11010: Ans<={1'b0,B};
      5'b01001: Ans<=A+B;
      5'b10001: Ans<={1'b0,A[3:0]~|B[3:0]};
	default: Ans=0;
	
    endcase
      
    Cout=Ans[4];
    Result<={Ans[3:0]};
   
  end
  
  always @(*)begin
  if (Ans[3:0]==4'b0)begin
      eq=1;	
    end
    else begin
      eq=0;
    end
	end
  endmodule

ROM.sv
/////////////////////////////
//Sang Woo Shin 15372
//ROMs
//Procesador
////////////////////////////

module ProgROM #(parameter N=12,M=8)(input logic [N-1:0] address, output logic[M-1:0] ProgOut);

	logic [N-1:0] memory [0:100];
	
	assign ProgOut=memory[address];
	
	initial begin
		$readmemb("CodeROM.list",memory);
	end
endmodule

module ControlROM #(parameter N=7,M=16)(input logic [N-1:0] address, output logic[M-1:0] ProgOut);

	always @(*)begin
		casex(address) //i3-i2-i1-i0-/C-/Z-Phase  
			7'bxxxxxx0: ProgOut<=16'b1111100000110111; //any
			7'b00000x1: ProgOut<=16'b0011100000110111; //JC
			7'b00001x1: ProgOut<=16'b1111100000110111; //JC
			7'b00010x1: ProgOut<=16'b1111100000110111; //JNC
			7'b00011x1: ProgOut<=16'b0011100000110111; //JNC
			7'b0010xx1: ProgOut<=16'b0110000110111101; //CMPI
			7'b0011xx1: ProgOut<=16'b1110000110011111; //CMPM
			7'b0100xx1: ProgOut<=16'b0100011010111101; //LIT
			7'b0101xx1: ProgOut<=16'b0100011010111011; //IN
			7'b0110xx1: ProgOut<=16'b1100011010011111; //LD
			7'b0111xx1: ProgOut<=16'b1111100000000111; //ST
			7'b1000x01: ProgOut<=16'b0011100000110111; //JZ
			7'b1000x11: ProgOut<=16'b1111100000110111; //JZ
			7'b1001x01: ProgOut<=16'b1111100000110111; //JNZ
			7'b1001x11: ProgOut<=16'b0011100000110111; //JNZ
			7'b1010xx1: ProgOut<=16'b0100101001111101; //ADDI
			7'b1011xx1: ProgOut<=16'b1100101001011111; //ADDM
			7'b1100xx1: ProgOut<=16'b0011100000110111; //JMP
			7'b1101xx1: ProgOut<=16'b0111100000110110; //OUT
			7'b1110xx1: ProgOut<=16'b0100010001111101; //NORI
			7'b1111xx1: ProgOut<=16'b1100010001011111; //NORM
			default: 	ProgOut<=16'b0111100000111111;
		endcase
	
	end
endmodule

ProgramCounter.sv
//---------------------------------------
//Sang Woo Shin 15372
//Lab 7 - PC
//----------------------------------------



module PC #(parameter N=12)(input logic [N-1:0] LOAD, input logic reset,loadE,incPC, clk, output logic [N-1:0] INS);
  
  always @ (posedge clk or posedge reset)begin
    if (reset)begin
    INS<=0;
    end
    else begin
      
      if (loadE)INS<=LOAD;
      
      if (incPC) INS<=INS+1;
      
    end
    
  end
    
endmodule

Board.sv
/////////////////////////////
//Sang Woo Shin 15372
//Breadboard-PCB
//Procesador
////////////////////////////

`include "ProgramCounter.sv"
`include "ALU.sv"
`include "FlipFlops.sv"
`include "ROM.sv"
`include "TristateBuffer.sv"
`include "RAM.sv"
`include "DecoderIO.sv"

module Board #(parameter N=4)(input logic clk, reset, input logic [N-1:0] In0,In1,In2, output logic C,Z, output logic [N-1:0] Out0,Out1,Out2,Accu, output logic [3:0] test);

wire [15:0] control;
wire [3:0] operand,ALUR,Aout;
wire [11:0] address,loadAdd;
wire [7:0] progbyte;
wire [6:0] uRomAddress;
wire [1:0] CarryZero;
wire [3:0] databus;
wire [15:0] outputE;
wire [15:0] inputE;


PC ProgCounter(.LOAD(loadAdd),.reset(reset),.loadE(~control[14]),.incPC(control[15]),.clk(clk),.INS(address));

FFT Phase(.clk(clk),.reset(reset),.T(1'b1),.Q(uRomAddress[0]));

FFD2 CZ(.clk((control[12] && ~uRomAddress[0])),.reset(reset),.D(~CarryZero),.Q(uRomAddress[2:1]));

ControlROM uROM(.address(uRomAddress),.ProgOut(control));

ProgROM pROM(.address(address),.ProgOut(progbyte));

FFD8 Fetch(.clk(uRomAddress[0]),.reset(reset),.D(progbyte),.Q({uRomAddress[6:3],operand}));

TristateB Oper(.tri_en(~control[1] ),.entrada(operand),.salida(databus));

FFD4 A(.clk(~control[13] && ~uRomAddress[0]),.reset(reset),.D(ALUR),.Q(Aout));

ALU ALU(.A(Aout),.B(databus),.S(control[10:6]),.nCin(control[11]),.Cout(CarryZero[1]),.eq(CarryZero[0]),.Result(ALUR));

TristateB TriALU(.tri_en(~control[3]),.entrada(ALUR),.salida(databus));

RAM DRAM(.clk(clk), .we(~control[4]), .cs(~control[5]), .address(loadAdd),.data(databus));

Decoder OutDecode(.load(~control[0]),.clk(control[13]),.binary(operand),.onehot(outputE)); //maybe clk(clk)

Decoder InputDecode(.load(~control[2]),.clk(control[13]),.binary(operand),.onehot(inputE));

TristateB Input0(.tri_en(inputE[0]),.entrada(In0),.salida(databus));

TristateB Input1(.tri_en(inputE[1]),.entrada(In1),.salida(databus));

TristateB Input2(.tri_en(inputE[2]),.entrada(In2),.salida(databus));

FFD4 Output0(.clk(outputE[0]  && ~uRomAddress[0]),.reset(reset),.D(databus),.Q(Out0));

FFD4 Output1(.clk(outputE[1] && ~uRomAddress[0]),.reset(reset),.D(databus),.Q(Out1));

FFD4 Output2(.clk(outputE[2]  && ~uRomAddress[0]),.reset(reset),.D(databus),.Q(Out2));

assign loadAdd= {operand,progbyte};

assign Accu = Aout;

assign C = ~uRomAddress[2];

assign Z = ~uRomAddress[1];

assign test=databus;




endmodule

tbProcessor.sv
`include "Board.sv"


module testbench();
  logic clk = 1, reset;
  logic [3:0] PUSHBUTTONS0, PUSHBUTTONS1, PUSHBUTTONS2;
  logic PHASE, C_FLAG, Z_FLAG;
  logic [3:0] INSTR, OPERAND, DATA_BUS, ACCU, PORT0, PORT1, PORT2;
  logic [7:0] PROGRAM_BYTE;
  logic [11:0] PC, ADDRESS_RAM;
  real points = 0;

  Board Proto(.clk(clk), .reset(reset), .In0(PUSHBUTTONS0), .In1(PUSHBUTTONS1), .In2(PUSHBUTTONS2), 
  .C(C_FLAG), .Z(Z_FLAG), .Out0(PORT0), .Out1(PORT1), .Out2(PORT2), .Accu(ACCU));

  initial begin
    reset = 0;
    #1 reset = 1;
    #1 reset = 0;
    PUSHBUTTONS0 = 4'b0110;
    PUSHBUTTONS1 = 4'b0100;
    PUSHBUTTONS2 = 4'b0001;
    //$display("\t\ttime:\tphase:\tPC:\tProgramByte:\tInstr:\tOprnd:\tRAM Addr:\tData Bus:\tAccu:\tC:\tZ:\tOut:\tIn:\t");
    //$monitor("%d\t%b\t%h\t%b\t%b\t%b\t%b\t%b\t\t%b\t%b\t%b\t%b\t%b", $time, PHASE, PC, PROGRAM_BYTE, INSTR, OPERAND, ADDRESS_RAM, DATA_BUS, ACCU, C_FLAG, Z_FLAG, FF_OUT, PUSHBUTTONS);
  end
  initial
    begin
  	  $dumpfile("dump.vcd");
  	  $dumpvars(1);
    end

  initial
    #1000 $finish;

  always
    #5 clk = ~clk;
	
	
   always @ (clk) begin
    case ($time)
      30: begin
        if (ACCU === 4'b1001) begin
          points = points + 5; $display("LIT funciona bien. Nota : %d", points); end
        else
          $display("LIT NO funciona bien. Nota: %d", points);
      end
      50: begin
        if (ACCU === 4'b1010) begin
          points = points + 5; $display("ADDI funciona bien. Nota : %d", points); end
        else
          $display("ADDI NO funciona bien. Nota: %d", points);
      end
      70: begin
        if (ACCU === 4'b0101) begin
          points = points + 5; $display("NORI funciona bien. Nota : %d", points); end
        else
          $display("NORI NO funciona bien. Nota: %d", points);
      end
      110: begin
        if (Z_FLAG === 1) begin
          points = points + 10; $display("CMPI & Z_FLAG funcionan bien. Nota: %d", points);
          $display("Felicitaciones! Todas las instrucciones con literales funcionan :)");
        end
        else
          $display("CMPI & Z_FLAG NO funcionan bien. Nota: %d", points);
      end
      150: begin
        if (ACCU === 4'b0000 && C_FLAG === 1) begin
          points = points + 5; $display("C_FLAG funciona bien. Nota : %d", points);
          $display("Felicitaciones! Todas las banderas funcionan bien! :D");
        end
        else
          $display("C_FLAG NO funciona bien. Nota: %d", points);
      end
      230: begin
      if (ACCU === 4'b1111) begin
        points = points + 15; $display("RAM (ST & LD) funciona bien. Nota : %d", points);
      end
      else
        $display("RAM (ST & LD) NO funciona bien. Nota: %d", points);
    end
      270: begin
        if (PORT0 === 4'b1000)
          $display("PORT0 funciona bien.");
        else
          $display("PORT0 NO funciona bien.");
      end
      310: begin
        if (PORT1 === 4'b0110)
          $display("PORT1 funciona bien.");
        else
          $display("PORT1 NO funciona bien.");
      end
      350: begin
        if (PORT2 === 4'b0001) begin
          points = points + 10; $display("PORT2 funciona bien. Nota: %d", points); end
        else
          $display("PORT2 NO funciona bien.");
      end
      370: begin
        if (ACCU === 4'b0110)
          $display("IN0 funciona bien.");
        else
          $display("IN0 NO funciona bien.");
      end
      390: begin
        if (ACCU === 4'b0100)
          $display("IN1 funciona bien.");
        else
          $display("IN1 NO funciona bien.");
      end
      410: begin
        if (ACCU === 4'b0001) begin
          points = points + 10; $display("IN2 funciona bien. Nota: %d", points); end
        else
          $display("IN2 NO funciona bien.");
      end
      470: begin
        if (ACCU === 4'b0000 && Z_FLAG === 1 && C_FLAG === 1) begin
          points = points + 5; $display("ADDM funciona bien. Nota: %d", points); end
        else
          $display("ADDM NO funciona bien.");
      end
      510: begin
        if (ACCU === 4'b0110) begin
          points = points + 5; $display("NORM funciona bien. Nota: %d", points); end
        else
          $display("NORM NO funciona bien.");
      end
      530: begin
        if (Z_FLAG === 0) begin
          $display("CMPM parece funcionar bien. Nota: %d", points); end
        else
          $display("CMPM NO funciona bien.");
      end
      570: begin
        if (Z_FLAG === 1) begin
          points = points + 5; $display("CMPM funciona bien. Nota: %d", points); end
        else
          $display("CMPM NO funciona bien.");
      end
      610: begin
        if (ACCU === 4'b1010) begin
          points = points + 4; $display("JMP funciona bien. Nota: %d", points); end
        else
          $display("JMP NO funciona bien.");
      end
      650: begin
        if (ACCU === 4'b1011) begin
          points = points + 4; $display("JNC funciona bien. Nota: %d", points); end
        else
          $display("JNC NO funciona bien.");
      end
      690: begin
        if (ACCU === 4'b1100) begin
          points = points + 4; $display("JNZ funciona bien. Nota: %d", points); end
        else
          $display("JNZ NO funciona bien.");
      end
      750: begin
        if (ACCU === 4'b0001) begin
          points = points + 4; $display("JZ funciona bien. Nota: %d", points); end
        else
          $display("JZ NO funciona bien.");
      end
      810: begin
        if (ACCU === 4'b0010) begin
          points = points + 4; $display("JC funciona bien. Nota: %d", points); end
        else
          $display("JC NO funciona bien.");
      end
    endcase
  end
endmodule

dumpp.vcd
$date
	Fri Nov 16 17:15:27 2018
$end
$version
	Icarus Verilog
$end
$timescale
	1s
$end
$scope module testbench $end
$var wire 1 ! Z_FLAG $end
$var wire 8 " PROGRAM_BYTE [7:0] $end
$var wire 4 # PORT2 [3:0] $end
$var wire 4 $ PORT1 [3:0] $end
$var wire 4 % PORT0 [3:0] $end
$var wire 1 & PHASE $end
$var wire 12 ' PC [11:0] $end
$var wire 4 ( OPERAND [3:0] $end
$var wire 4 ) INSTR [3:0] $end
$var wire 4 * DATA_BUS [3:0] $end
$var wire 1 + C_FLAG $end
$var wire 12 , ADDRESS_RAM [11:0] $end
$var wire 4 - ACCU [3:0] $end
$var reg 4 . PUSHBUTTONS0 [3:0] $end
$var reg 4 / PUSHBUTTONS1 [3:0] $end
$var reg 4 0 PUSHBUTTONS2 [3:0] $end
$var reg 1 1 clk $end
$var reg 1 2 reset $end
$var real 1 3 points $end
$upscope $end
$enddefinitions $end
#0
$dumpvars
r0 3
02
11
bx 0
bx /
bx .
bx -
bx ,
x+
bx *
bx )
bx (
bx '
x&
bx %
bx $
bx #
bx "
x!
$end
#1
b0 *
b0 (
b0 )
b0 #
b0 $
b0 %
b0 -
0&
0+
0!
b1001001 ,
b1001001 "
b0 '
12
#2
b1 0
b100 /
b110 .
02
#5
01
#10
b1001 *
b1001 (
b100 )
b100110100001 ,
b10100001 "
b1 '
1&
11
#15
01
#20
r5 3
b1001 -
0&
11
#25
01
#30
b1 *
b1 (
b1010 )
b111101010 ,
b11101010 "
b10 '
1&
11
#35
01
#40
b1010 *
b1010 -
0&
11
#45
01
#50
b1010 *
b1010 (
b1110 )
b101000100110 ,
b100110 "
b11 '
1&
11
#55
01
#60
b101 *
b101 -
0&
11
#65
01
#70
b110 *
b110 (
b10 )
b11000100101 ,
b100101 "
b100 '
1&
11
#75
01
#80
b101 *
0&
1+
11
#85
01
#90
b101 *
b101 (
b10101001111 ,
b1001111 "
b101 '
1&
11
#95
01
#100
0&
0+
1!
11
#105
01
#110
b1111 *
b1111 (
b100 )
b111110100001 ,
b10100001 "
b110 '
1&
11
#115
01
#120
b1111 -
0&
0!
11
#125
01
#130
b1 *
b1 (
b1010 )
b101001111 ,
b1001111 "
b111 '
1&
11
#135
01
#140
b0 *
b0 -
0&
1+
1!
11
#145
01
#150
b1111 *
b1111 (
b100 )
b111101110000 ,
b1110000 "
b1000 '
1&
11
#155
01
#160
b1111 -
0&
0+
0!
11
#165
01
#170
b0 (
b111 )
b1 ,
b1 "
b1001 '
1&
11
#175
01
#180
0&
b1000001 ,
b1000001 "
b1010 '
11
#185
01
#190
b1 *
b1 (
b100 )
b101100000 ,
b1100000 "
b1011 '
1&
11
#195
01
#200
b1 -
0&
11
#205
01
#210
b1111 *
b0 (
b110 )
b1 ,
b1 "
b1100 '
1&
11
#215
01
#220
b1111 *
b1111 -
0&
b11010000 ,
b11010000 "
b1101 '
11
#225
01
#230
b1101 )
b1000110 ,
b1000110 "
b1110 '
1&
11
#235
01
#240
b1111 %
0&
11
#245
01
#250
b110 *
b110 (
b100 )
b11011010001 ,
b11010001 "
b1111 '
1&
11
#255
01
#260
b110 -
0&
11
#265
01
#270
b1 (
b1101 )
b101000001 ,
b1000001 "
b10000 '
1&
11
#275
01
#280
b110 $
0&
11
#285
01
#290
b1 *
b100 )
b111010010 ,
b11010010 "
b10001 '
1&
11
#295
01
#300
b1 -
0&
11
#305
01
#310
b10 (
b1101 )
b1001010000 ,
b1010000 "
b10010 '
1&
11
#315
01
#320
b1 #
0&
11
#325
01
#330
b110 *
b0 (
b101 )
b1010001 ,
b1010001 "
b10011 '
1&
11
#335
01
#340
b110 -
0&
11
#345
01
#350
b100 *
b1 (
b101010010 ,
b1010010 "
b10100 '
1&
11
#355
01
#360
b100 -
0&
11
#365
01
#370
b1 *
b10 (
b1001111111 ,
b1111111 "
b10101 '
1&
11
#375
01
#380
b1 -
0&
11
#385
01
#390
b1111 (
b111 )
b111111111111 ,
b11111111 "
b10110 '
1&
11
#395
01
#400
0&
b111101001111 ,
b1001111 "
b10111 '
11
#405
01
#410
b1111 *
b100 )
b111110111111 ,
b10111111 "
b11000 '
1&
11
#415
01
#420
b1111 -
0&
11
#425
01
#430
b1 *
b1011 )
b111111111111 ,
b11111111 "
b11001 '
1&
11
#435
01
#440
b0 *
b0 -
0&
1+
1!
b111101001000 ,
b1001000 "
b11010 '
11
#445
01
#450
b1000 *
b1000 (
b100 )
b100011111111 ,
b11111111 "
b11011 '
1&
11
#455
01
#460
b1000 -
0&
0+
0!
11
#465
01
#470
b1 *
b111111111111 ,
b1111 (
b1111 )
b11100 '
1&
11
#475
01
#480
b110 *
b110 -
0&
b111100111111 ,
b111111 "
b11101 '
11
#485
01
#490
b1 *
b11 )
b111111111111 ,
b11111111 "
b11110 '
1&
11
#495
01
#500
b110 *
0&
b111101000001 ,
b1000001 "
b11111 '
11
#505
01
#510
b1 *
b1 (
b100 )
b100111111 ,
b111111 "
b100000 '
1&
11
#515
01
#520
b1 -
0&
11
#525
01
#530
b1 *
b1111 (
b11 )
b111111111111 ,
b11111111 "
b100001 '
1&
11
#535
01
#540
b1 *
0&
1!
b1111xxxxxxxx ,
bx "
b100010 '
11
#545
01
#550
bx ,
bx (
bx )
b100011 '
1&
11
#555
01
#560
0&
b100100 '
11
#565
01
#570
b100101 '
1&
11
#575
01
#580
0&
b100110 '
11
#585
01
#590
b100111 '
1&
11
#595
01
#600
0&
b101000 '
11
#605
01
#610
b101001 '
1&
11
#615
01
#620
0&
b101010 '
11
#625
01
#630
b101011 '
1&
11
#635
01
#640
0&
b101100 '
11
#645
01
#650
b101101 '
1&
11
#655
01
#660
0&
b101110 '
11
#665
01
#670
b101111 '
1&
11
#675
01
#680
0&
b110000 '
11
#685
01
#690
b110001 '
1&
11
#695
01
#700
0&
b110010 '
11
#705
01
#710
b110011 '
1&
11
#715
01
#720
0&
b110100 '
11
#725
01
#730
b110101 '
1&
11
#735
01
#740
0&
b110110 '
11
#745
01
#750
b110111 '
1&
11
#755
01
#760
0&
b111000 '
11
#765
01
#770
b111001 '
1&
11
#775
01
#780
0&
b111010 '
11
#785
01
#790
b111011 '
1&
11
#795
01
#800
0&
b111100 '
11
#805
01
#810
b111101 '
1&
11
#815
01
#820
0&
b111110 '
11
#825
01
#830
b111111 '
1&
11
#835
01
#840
0&
b1000000 '
11
#845
01
#850
b1000001 '
1&
11
#855
01
#860
0&
b1000010 '
11
#865
01
#870
b1000011 '
1&
11
#875
01
#880
0&
b1000100 '
11
#885
01
#890
b1000101 '
1&
11
#895
01
#900
0&
b1000110 '
11
#905
01
#910
b1000111 '
1&
11
#915
01
#920
0&
b1001000 '
11
#925
01
#930
b1001001 '
1&
11
#935
01
#940
0&
b1001010 '
11
#945
01
#950
b1001011 '
1&
11
#955
01
#960
0&
b1001100 '
11
#965
01
#970
b1001101 '
1&
11
#975
01
#980
0&
b1001110 '
11
#985
01
#990
b1001111 '
1&
11
#995
01
#1000
0&
b1010000 '
11
